clk_gen/clk_20k_gen.v
module clk_20k_gen
(
    input           clk     ,
    input           rst     ,

    output          clk_20k 
);

    reg             clk_20k_r;
    reg     [13:0]   cnt;

    always @ (posedge clk, negedge rst) begin
        if (!rst) begin
            clk_20k_r <= 1'b0;
            cnt <= 14'd0;
        end
        else if (cnt < 14'd24) begin
            cnt <= cnt + 14'd1;
        end
        else if (cnt == 14'd24) begin
            cnt <= cnt + 14'd1;
            clk_20k_r <= 1'b1;
        end
        else if (cnt < 14'd49) begin
            cnt <= cnt + 14'd1;
        end
        else if (cnt == 14'd49) begin
            clk_20k_r <= 1'b0;
            cnt <= 14'd0;
        end
    end

    assign clk_20k = clk_20k_r;

endmodule

clk_gen/tb_clk_20k_gen.v
`timescale 1ns/1ps

module tb_clk_20k_gen;

    localparam  SIM_TIME= 10000000;
    
    reg         clk;
    reg         rst;

    wire        clk_20k;

    clk_20k_gen clk_20k_gen
    (
        .clk(clk)           ,
        .rst(rst)           ,

        .clk_20k(clk_20k)    
    );

    always #50 clk = ~clk;

    initial begin
        clk = 1'b0;
        rst = 1'b1;

        #10
        rst = 1'b0;
        #10
        rst = 1'b1;
    end

    initial begin
        $dumpfile("clk_20k_gen.vcd");
        $dumpvars(0, tb_clk_20k_gen);

        #(SIM_TIME);
        $finish;
    end

endmodule

clk_gen/clk_20k_gen.vcd
$date
	Mon Nov 13 01:05:31 2023
$end
$version
	Icarus Verilog
$end
$timescale
	1ps
$end
$scope module tb_clk_20k_gen $end
$var wire 1 ! clk_20k $end
$var reg 1 " clk $end
$var reg 1 # rst $end
$scope module clk_20k_gen $end
$var wire 1 " clk $end
$var wire 1 ! clk_20k $end
$var wire 1 # rst $end
$var reg 1 $ clk_20k_r $end
$var reg 14 % cnt [13:0] $end
$upscope $end
$upscope $end
$enddefinitions $end
#0
$dumpvars
bx %
x$
1#
0"
x!
$end
#10000
b0 %
0!
0$
0#
#20000
1#
#50000
b1 %
1"
#100000
0"
#150000
b10 %
1"
#200000
0"
#250000
b11 %
1"
#300000
0"
#350000
b100 %
1"
#400000
0"
#450000
b101 %
1"
#500000
0"
#550000
b110 %
1"
#600000
0"
#650000
b111 %
1"
#700000
0"
#750000
b1000 %
1"
#800000
0"
#850000
b1001 %
1"
#900000
0"
#950000
b1010 %
1"
#1000000
0"
#1050000
b1011 %
1"
#1100000
0"
#1150000
b1100 %
1"
#1200000
0"
#1250000
b1101 %
1"
#1300000
0"
#1350000
b1110 %
1"
#1400000
0"
#1450000
b1111 %
1"
#1500000
0"
#1550000
b10000 %
1"
#1600000
0"
#1650000
b10001 %
1"
#1700000
0"
#1750000
b10010 %
1"
#1800000
0"
#1850000
b10011 %
1"
#1900000
0"
#1950000
b10100 %
1"
#2000000
0"
#2050000
b10101 %
1"
#2100000
0"
#2150000
b10110 %
1"
#2200000
0"
#2250000
b10111 %
1"
#2300000
0"
#2350000
b11000 %
1"
#2400000
0"
#2450000
1!
1$
b11001 %
1"
#2500000
0"
#2550000
b11010 %
1"
#2600000
0"
#2650000
b11011 %
1"
#2700000
0"
#2750000
b11100 %
1"
#2800000
0"
#2850000
b11101 %
1"
#2900000
0"
#2950000
b11110 %
1"
#3000000
0"
#3050000
b11111 %
1"
#3100000
0"
#3150000
b100000 %
1"
#3200000
0"
#3250000
b100001 %
1"
#3300000
0"
#3350000
b100010 %
1"
#3400000
0"
#3450000
b100011 %
1"
#3500000
0"
#3550000
b100100 %
1"
#3600000
0"
#3650000
b100101 %
1"
#3700000
0"
#3750000
b100110 %
1"
#3800000
0"
#3850000
b100111 %
1"
#3900000
0"
#3950000
b101000 %
1"
#4000000
0"
#4050000
b101001 %
1"
#4100000
0"
#4150000
b101010 %
1"
#4200000
0"
#4250000
b101011 %
1"
#4300000
0"
#4350000
b101100 %
1"
#4400000
0"
#4450000
b101101 %
1"
#4500000
0"
#4550000
b101110 %
1"
#4600000
0"
#4650000
b101111 %
1"
#4700000
0"
#4750000
b110000 %
1"
#4800000
0"
#4850000
b110001 %
1"
#4900000
0"
#4950000
b0 %
0!
0$
1"
#5000000
0"
#5050000
b1 %
1"
#5100000
0"
#5150000
b10 %
1"
#5200000
0"
#5250000
b11 %
1"
#5300000
0"
#5350000
b100 %
1"
#5400000
0"
#5450000
b101 %
1"
#5500000
0"
#5550000
b110 %
1"
#5600000
0"
#5650000
b111 %
1"
#5700000
0"
#5750000
b1000 %
1"
#5800000
0"
#5850000
b1001 %
1"
#5900000
0"
#5950000
b1010 %
1"
#6000000
0"
#6050000
b1011 %
1"
#6100000
0"
#6150000
b1100 %
1"
#6200000
0"
#6250000
b1101 %
1"
#6300000
0"
#6350000
b1110 %
1"
#6400000
0"
#6450000
b1111 %
1"
#6500000
0"
#6550000
b10000 %
1"
#6600000
0"
#6650000
b10001 %
1"
#6700000
0"
#6750000
b10010 %
1"
#6800000
0"
#6850000
b10011 %
1"
#6900000
0"
#6950000
b10100 %
1"
#7000000
0"
#7050000
b10101 %
1"
#7100000
0"
#7150000
b10110 %
1"
#7200000
0"
#7250000
b10111 %
1"
#7300000
0"
#7350000
b11000 %
1"
#7400000
0"
#7450000
1!
1$
b11001 %
1"
#7500000
0"
#7550000
b11010 %
1"
#7600000
0"
#7650000
b11011 %
1"
#7700000
0"
#7750000
b11100 %
1"
#7800000
0"
#7850000
b11101 %
1"
#7900000
0"
#7950000
b11110 %
1"
#8000000
0"
#8050000
b11111 %
1"
#8100000
0"
#8150000
b100000 %
1"
#8200000
0"
#8250000
b100001 %
1"
#8300000
0"
#8350000
b100010 %
1"
#8400000
0"
#8450000
b100011 %
1"
#8500000
0"
#8550000
b100100 %
1"
#8600000
0"
#8650000
b100101 %
1"
#8700000
0"
#8750000
b100110 %
1"
#8800000
0"
#8850000
b100111 %
1"
#8900000
0"
#8950000
b101000 %
1"
#9000000
0"
#9050000
b101001 %
1"
#9100000
0"
#9150000
b101010 %
1"
#9200000
0"
#9250000
b101011 %
1"
#9300000
0"
#9350000
b101100 %
1"
#9400000
0"
#9450000
b101101 %
1"
#9500000
0"
#9550000
b101110 %
1"
#9600000
0"
#9650000
b101111 %
1"
#9700000
0"
#9750000
b110000 %
1"
#9800000
0"
#9850000
b110001 %
1"
#9900000
0"
#9950000
b0 %
0!
0$
1"
#10000000
0"
#10050000
b1 %
1"
#10100000
0"
#10150000
b10 %
1"
#10200000
0"
#10250000
b11 %
1"
#10300000
0"
#10350000
b100 %
1"
#10400000
0"
#10450000
b101 %
1"
#10500000
0"
#10550000
b110 %
1"
#10600000
0"
#10650000
b111 %
1"
#10700000
0"
#10750000
b1000 %
1"
#10800000
0"
#10850000
b1001 %
1"
#10900000
0"
#10950000
b1010 %
1"
#11000000
0"
#11050000
b1011 %
1"
#11100000
0"
#11150000
b1100 %
1"
#11200000
0"
#11250000
b1101 %
1"
#11300000
0"
#11350000
b1110 %
1"
#11400000
0"
#11450000
b1111 %
1"
#11500000
0"
#11550000
b10000 %
1"
#11600000
0"
#11650000
b10001 %
1"
#11700000
0"
#11750000
b10010 %
1"
#11800000
0"
#11850000
b10011 %
1"
#11900000
0"
#11950000
b10100 %
1"
#12000000
0"
#12050000
b10101 %
1"
#12100000
0"
#12150000
b10110 %
1"
#12200000
0"
#12250000
b10111 %
1"
#12300000
0"
#12350000
b11000 %
1"
#12400000
0"
#12450000
1!
1$
b11001 %
1"
#12500000
0"
#12550000
b11010 %
1"
#12600000
0"
#12650000
b11011 %
1"
#12700000
0"
#12750000
b11100 %
1"
#12800000
0"
#12850000
b11101 %
1"
#12900000
0"
#12950000
b11110 %
1"
#13000000
0"
#13050000
b11111 %
1"
#13100000
0"
#13150000
b100000 %
1"
#13200000
0"
#13250000
b100001 %
1"
#13300000
0"
#13350000
b100010 %
1"
#13400000
0"
#13450000
b100011 %
1"
#13500000
0"
#13550000
b100100 %
1"
#13600000
0"
#13650000
b100101 %
1"
#13700000
0"
#13750000
b100110 %
1"
#13800000
0"
#13850000
b100111 %
1"
#13900000
0"
#13950000
b101000 %
1"
#14000000
0"
#14050000
b101001 %
1"
#14100000
0"
#14150000
b101010 %
1"
#14200000
0"
#14250000
b101011 %
1"
#14300000
0"
#14350000
b101100 %
1"
#14400000
0"
#14450000
b101101 %
1"
#14500000
0"
#14550000
b101110 %
1"
#14600000
0"
#14650000
b101111 %
1"
#14700000
0"
#14750000
b110000 %
1"
#14800000
0"
#14850000
b110001 %
1"
#14900000
0"
#14950000
b0 %
0!
0$
1"
#15000000
0"
#15050000
b1 %
1"
#15100000
0"
#15150000
b10 %
1"
#15200000
0"
#15250000
b11 %
1"
#15300000
0"
#15350000
b100 %
1"
#15400000
0"
#15450000
b101 %
1"
#15500000
0"
#15550000
b110 %
1"
#15600000
0"
#15650000
b111 %
1"
#15700000
0"
#15750000
b1000 %
1"
#15800000
0"
#15850000
b1001 %
1"
#15900000
0"
#15950000
b1010 %
1"
#16000000
0"
#16050000
b1011 %
1"
#16100000
0"
#16150000
b1100 %
1"
#16200000
0"
#16250000
b1101 %
1"
#16300000
0"
#16350000
b1110 %
1"
#16400000
0"
#16450000
b1111 %
1"
#16500000
0"
#16550000
b10000 %
1"
#16600000
0"
#16650000
b10001 %
1"
#16700000
0"
#16750000
b10010 %
1"
#16800000
0"
#16850000
b10011 %
1"
#16900000
0"
#16950000
b10100 %
1"
#17000000
0"
#17050000
b10101 %
1"
#17100000
0"
#17150000
b10110 %
1"
#17200000
0"
#17250000
b10111 %
1"
#17300000
0"
#17350000
b11000 %
1"
#17400000
0"
#17450000
1!
1$
b11001 %
1"
#17500000
0"
#17550000
b11010 %
1"
#17600000
0"
#17650000
b11011 %
1"
#17700000
0"
#17750000
b11100 %
1"
#17800000
0"
#17850000
b11101 %
1"
#17900000
0"
#17950000
b11110 %
1"
#18000000
0"
#18050000
b11111 %
1"
#18100000
0"
#18150000
b100000 %
1"
#18200000
0"
#18250000
b100001 %
1"
#18300000
0"
#18350000
b100010 %
1"
#18400000
0"
#18450000
b100011 %
1"
#18500000
0"
#18550000
b100100 %
1"
#18600000
0"
#18650000
b100101 %
1"
#18700000
0"
#18750000
b100110 %
1"
#18800000
0"
#18850000
b100111 %
1"
#18900000
0"
#18950000
b101000 %
1"
#19000000
0"
#19050000
b101001 %
1"
#19100000
0"
#19150000
b101010 %
1"
#19200000
0"
#19250000
b101011 %
1"
#19300000
0"
#19350000
b101100 %
1"
#19400000
0"
#19450000
b101101 %
1"
#19500000
0"
#19550000
b101110 %
1"
#19600000
0"
#19650000
b101111 %
1"
#19700000
0"
#19750000
b110000 %
1"
#19800000
0"
#19850000
b110001 %
1"
#19900000
0"
#19950000
b0 %
0!
0$
1"
#20000000
0"
#20050000
b1 %
1"
#20100000
0"
#20150000
b10 %
1"
#20200000
0"
#20250000
b11 %
1"
#20300000
0"
#20350000
b100 %
1"
#20400000
0"
#20450000
b101 %
1"
#20500000
0"
#20550000
b110 %
1"
#20600000
0"
#20650000
b111 %
1"
#20700000
0"
#20750000
b1000 %
1"
#20800000
0"
#20850000
b1001 %
1"
#20900000
0"
#20950000
b1010 %
1"
#21000000
0"
#21050000
b1011 %
1"
#21100000
0"
#21150000
b1100 %
1"
#21200000
0"
#21250000
b1101 %
1"
#21300000
0"
#21350000
b1110 %
1"
#21400000
0"
#21450000
b1111 %
1"
#21500000
0"
#21550000
b10000 %
1"
#21600000
0"
#21650000
b10001 %
1"
#21700000
0"
#21750000
b10010 %
1"
#21800000
0"
#21850000
b10011 %
1"
#21900000
0"
#21950000
b10100 %
1"
#22000000
0"
#22050000
b10101 %
1"
#22100000
0"
#22150000
b10110 %
1"
#22200000
0"
#22250000
b10111 %
1"
#22300000
0"
#22350000
b11000 %
1"
#22400000
0"
#22450000
1!
1$
b11001 %
1"
#22500000
0"
#22550000
b11010 %
1"
#22600000
0"
#22650000
b11011 %
1"
#22700000
0"
#22750000
b11100 %
1"
#22800000
0"
#22850000
b11101 %
1"
#22900000
0"
#22950000
b11110 %
1"
#23000000
0"
#23050000
b11111 %
1"
#23100000
0"
#23150000
b100000 %
1"
#23200000
0"
#23250000
b100001 %
1"
#23300000
0"
#23350000
b100010 %
1"
#23400000
0"
#23450000
b100011 %
1"
#23500000
0"
#23550000
b100100 %
1"
#23600000
0"
#23650000
b100101 %
1"
#23700000
0"
#23750000
b100110 %
1"
#23800000
0"
#23850000
b100111 %
1"
#23900000
0"
#23950000
b101000 %
1"
#24000000
0"
#24050000
b101001 %
1"
#24100000
0"
#24150000
b101010 %
1"
#24200000
0"
#24250000
b101011 %
1"
#24300000
0"
#24350000
b101100 %
1"
#24400000
0"
#24450000
b101101 %
1"
#24500000
0"
#24550000
b101110 %
1"
#24600000
0"
#24650000
b101111 %
1"
#24700000
0"
#24750000
b110000 %
1"
#24800000
0"
#24850000
b110001 %
1"
#24900000
0"
#24950000
b0 %
0!
0$
1"
#25000000
0"
#25050000
b1 %
1"
#25100000
0"
#25150000
b10 %
1"
#25200000
0"
#25250000
b11 %
1"
#25300000
0"
#25350000
b100 %
1"
#25400000
0"
#25450000
b101 %
1"
#25500000
0"
#25550000
b110 %
1"
#25600000
0"
#25650000
b111 %
1"
#25700000
0"
#25750000
b1000 %
1"
#25800000
0"
#25850000
b1001 %
1"
#25900000
0"
#25950000
b1010 %
1"
#26000000
0"
#26050000
b1011 %
1"
#26100000
0"
#26150000
b1100 %
1"
#26200000
0"
#26250000
b1101 %
1"
#26300000
0"
#26350000
b1110 %
1"
#26400000
0"
#26450000
b1111 %
1"
#26500000
0"
#26550000
b10000 %
1"
#26600000
0"
#26650000
b10001 %
1"
#26700000
0"
#26750000
b10010 %
1"
#26800000
0"
#26850000
b10011 %
1"
#26900000
0"
#26950000
b10100 %
1"
#27000000
0"
#27050000
b10101 %
1"
#27100000
0"
#27150000
b10110 %
1"
#27200000
0"
#27250000
b10111 %
1"
#27300000
0"
#27350000
b11000 %
1"
#27400000
0"
#27450000
1!
1$
b11001 %
1"
#27500000
0"
#27550000
b11010 %
1"
#27600000
0"
#27650000
b11011 %
1"
#27700000
0"
#27750000
b11100 %
1"
#27800000
0"
#27850000
b11101 %
1"
#27900000
0"
#27950000
b11110 %
1"
#28000000
0"
#28050000
b11111 %
1"
#28100000
0"
#28150000
b100000 %
1"
#28200000
0"
#28250000
b100001 %
1"
#28300000
0"
#28350000
b100010 %
1"
#28400000
0"
#28450000
b100011 %
1"
#28500000
0"
#28550000
b100100 %
1"
#28600000
0"
#28650000
b100101 %
1"
#28700000
0"
#28750000
b100110 %
1"
#28800000
0"
#28850000
b100111 %
1"
#28900000
0"
#28950000
b101000 %
1"
#29000000
0"
#29050000
b101001 %
1"
#29100000
0"
#29150000
b101010 %
1"
#29200000
0"
#29250000
b101011 %
1"
#29300000
0"
#29350000
b101100 %
1"
#29400000
0"
#29450000
b101101 %
1"
#29500000
0"
#29550000
b101110 %
1"
#29600000
0"
#29650000
b101111 %
1"
#29700000
0"
#29750000
b110000 %
1"
#29800000
0"
#29850000
b110001 %
1"
#29900000
0"
#29950000
b0 %
0!
0$
1"
#30000000
0"
#30050000
b1 %
1"
#30100000
0"
#30150000
b10 %
1"
#30200000
0"
#30250000
b11 %
1"
#30300000
0"
#30350000
b100 %
1"
#30400000
0"
#30450000
b101 %
1"
#30500000
0"
#30550000
b110 %
1"
#30600000
0"
#30650000
b111 %
1"
#30700000
0"
#30750000
b1000 %
1"
#30800000
0"
#30850000
b1001 %
1"
#30900000
0"
#30950000
b1010 %
1"
#31000000
0"
#31050000
b1011 %
1"
#31100000
0"
#31150000
b1100 %
1"
#31200000
0"
#31250000
b1101 %
1"
#31300000
0"
#31350000
b1110 %
1"
#31400000
0"
#31450000
b1111 %
1"
#31500000
0"
#31550000
b10000 %
1"
#31600000
0"
#31650000
b10001 %
1"
#31700000
0"
#31750000
b10010 %
1"
#31800000
0"
#31850000
b10011 %
1"
#31900000
0"
#31950000
b10100 %
1"
#32000000
0"
#32050000
b10101 %
1"
#32100000
0"
#32150000
b10110 %
1"
#32200000
0"
#32250000
b10111 %
1"
#32300000
0"
#32350000
b11000 %
1"
#32400000
0"
#32450000
1!
1$
b11001 %
1"
#32500000
0"
#32550000
b11010 %
1"
#32600000
0"
#32650000
b11011 %
1"
#32700000
0"
#32750000
b11100 %
1"
#32800000
0"
#32850000
b11101 %
1"
#32900000
0"
#32950000
b11110 %
1"
#33000000
0"
#33050000
b11111 %
1"
#33100000
0"
#33150000
b100000 %
1"
#33200000
0"
#33250000
b100001 %
1"
#33300000
0"
#33350000
b100010 %
1"
#33400000
0"
#33450000
b100011 %
1"
#33500000
0"
#33550000
b100100 %
1"
#33600000
0"
#33650000
b100101 %
1"
#33700000
0"
#33750000
b100110 %
1"
#33800000
0"
#33850000
b100111 %
1"
#33900000
0"
#33950000
b101000 %
1"
#34000000
0"
#34050000
b101001 %
1"
#34100000
0"
#34150000
b101010 %
1"
#34200000
0"
#34250000
b101011 %
1"
#34300000
0"
#34350000
b101100 %
1"
#34400000
0"
#34450000
b101101 %
1"
#34500000
0"
#34550000
b101110 %
1"
#34600000
0"
#34650000
b101111 %
1"
#34700000
0"
#34750000
b110000 %
1"
#34800000
0"
#34850000
b110001 %
1"
#34900000
0"
#34950000
b0 %
0!
0$
1"
#35000000
0"
#35050000
b1 %
1"
#35100000
0"
#35150000
b10 %
1"
#35200000
0"
#35250000
b11 %
1"
#35300000
0"
#35350000
b100 %
1"
#35400000
0"
#35450000
b101 %
1"
#35500000
0"
#35550000
b110 %
1"
#35600000
0"
#35650000
b111 %
1"
#35700000
0"
#35750000
b1000 %
1"
#35800000
0"
#35850000
b1001 %
1"
#35900000
0"
#35950000
b1010 %
1"
#36000000
0"
#36050000
b1011 %
1"
#36100000
0"
#36150000
b1100 %
1"
#36200000
0"
#36250000
b1101 %
1"
#36300000
0"
#36350000
b1110 %
1"
#36400000
0"
#36450000
b1111 %
1"
#36500000
0"
#36550000
b10000 %
1"
#36600000
0"
#36650000
b10001 %
1"
#36700000
0"
#36750000
b10010 %
1"
#36800000
0"
#36850000
b10011 %
1"
#36900000
0"
#36950000
b10100 %
1"
#37000000
0"
#37050000
b10101 %
1"
#37100000
0"
#37150000
b10110 %
1"
#37200000
0"
#37250000
b10111 %
1"
#37300000
0"
#37350000
b11000 %
1"
#37400000
0"
#37450000
1!
1$
b11001 %
1"
#37500000
0"
#37550000
b11010 %
1"
#37600000
0"
#37650000
b11011 %
1"
#37700000
0"
#37750000
b11100 %
1"
#37800000
0"
#37850000
b11101 %
1"
#37900000
0"
#37950000
b11110 %
1"
#38000000
0"
#38050000
b11111 %
1"
#38100000
0"
#38150000
b100000 %
1"
#38200000
0"
#38250000
b100001 %
1"
#38300000
0"
#38350000
b100010 %
1"
#38400000
0"
#38450000
b100011 %
1"
#38500000
0"
#38550000
b100100 %
1"
#38600000
0"
#38650000
b100101 %
1"
#38700000
0"
#38750000
b100110 %
1"
#38800000
0"
#38850000
b100111 %
1"
#38900000
0"
#38950000
b101000 %
1"
#39000000
0"
#39050000
b101001 %
1"
#39100000
0"
#39150000
b101010 %
1"
#39200000
0"
#39250000
b101011 %
1"
#39300000
0"
#39350000
b101100 %
1"
#39400000
0"
#39450000
b101101 %
1"
#39500000
0"
#39550000
b101110 %
1"
#39600000
0"
#39650000
b101111 %
1"
#39700000
0"
#39750000
b110000 %
1"
#39800000
0"
#39850000
b110001 %
1"
#39900000
0"
#39950000
b0 %
0!
0$
1"
#40000000
0"
#40050000
b1 %
1"
#40100000
0"
#40150000
b10 %
1"
#40200000
0"
#40250000
b11 %
1"
#40300000
0"
#40350000
b100 %
1"
#40400000
0"
#40450000
b101 %
1"
#40500000
0"
#40550000
b110 %
1"
#40600000
0"
#40650000
b111 %
1"
#40700000
0"
#40750000
b1000 %
1"
#40800000
0"
#40850000
b1001 %
1"
#40900000
0"
#40950000
b1010 %
1"
#41000000
0"
#41050000
b1011 %
1"
#41100000
0"
#41150000
b1100 %
1"
#41200000
0"
#41250000
b1101 %
1"
#41300000
0"
#41350000
b1110 %
1"
#41400000
0"
#41450000
b1111 %
1"
#41500000
0"
#41550000
b10000 %
1"
#41600000
0"
#41650000
b10001 %
1"
#41700000
0"
#41750000
b10010 %
1"
#41800000
0"
#41850000
b10011 %
1"
#41900000
0"
#41950000
b10100 %
1"
#42000000
0"
#42050000
b10101 %
1"
#42100000
0"
#42150000
b10110 %
1"
#42200000
0"
#42250000
b10111 %
1"
#42300000
0"
#42350000
b11000 %
1"
#42400000
0"
#42450000
1!
1$
b11001 %
1"
#42500000
0"
#42550000
b11010 %
1"
#42600000
0"
#42650000
b11011 %
1"
#42700000
0"
#42750000
b11100 %
1"
#42800000
0"
#42850000
b11101 %
1"
#42900000
0"
#42950000
b11110 %
1"
#43000000
0"
#43050000
b11111 %
1"
#43100000
0"
#43150000
b100000 %
1"
#43200000
0"
#43250000
b100001 %
1"
#43300000
0"
#43350000
b100010 %
1"
#43400000
0"
#43450000
b100011 %
1"
#43500000
0"
#43550000
b100100 %
1"
#43600000
0"
#43650000
b100101 %
1"
#43700000
0"
#43750000
b100110 %
1"
#43800000
0"
#43850000
b100111 %
1"
#43900000
0"
#43950000
b101000 %
1"
#44000000
0"
#44050000
b101001 %
1"
#44100000
0"
#44150000
b101010 %
1"
#44200000
0"
#44250000
b101011 %
1"
#44300000
0"
#44350000
b101100 %
1"
#44400000
0"
#44450000
b101101 %
1"
#44500000
0"
#44550000
b101110 %
1"
#44600000
0"
#44650000
b101111 %
1"
#44700000
0"
#44750000
b110000 %
1"
#44800000
0"
#44850000
b110001 %
1"
#44900000
0"
#44950000
b0 %
0!
0$
1"
#45000000
0"
#45050000
b1 %
1"
#45100000
0"
#45150000
b10 %
1"
#45200000
0"
#45250000
b11 %
1"
#45300000
0"
#45350000
b100 %
1"
#45400000
0"
#45450000
b101 %
1"
#45500000
0"
#45550000
b110 %
1"
#45600000
0"
#45650000
b111 %
1"
#45700000
0"
#45750000
b1000 %
1"
#45800000
0"
#45850000
b1001 %
1"
#45900000
0"
#45950000
b1010 %
1"
#46000000
0"
#46050000
b1011 %
1"
#46100000
0"
#46150000
b1100 %
1"
#46200000
0"
#46250000
b1101 %
1"
#46300000
0"
#46350000
b1110 %
1"
#46400000
0"
#46450000
b1111 %
1"
#46500000
0"
#46550000
b10000 %
1"
#46600000
0"
#46650000
b10001 %
1"
#46700000
0"
#46750000
b10010 %
1"
#46800000
0"
#46850000
b10011 %
1"
#46900000
0"
#46950000
b10100 %
1"
#47000000
0"
#47050000
b10101 %
1"
#47100000
0"
#47150000
b10110 %
1"
#47200000
0"
#47250000
b10111 %
1"
#47300000
0"
#47350000
b11000 %
1"
#47400000
0"
#47450000
1!
1$
b11001 %
1"
#47500000
0"
#47550000
b11010 %
1"
#47600000
0"
#47650000
b11011 %
1"
#47700000
0"
#47750000
b11100 %
1"
#47800000
0"
#47850000
b11101 %
1"
#47900000
0"
#47950000
b11110 %
1"
#48000000
0"
#48050000
b11111 %
1"
#48100000
0"
#48150000
b100000 %
1"
#48200000
0"
#48250000
b100001 %
1"
#48300000
0"
#48350000
b100010 %
1"
#48400000
0"
#48450000
b100011 %
1"
#48500000
0"
#48550000
b100100 %
1"
#48600000
0"
#48650000
b100101 %
1"
#48700000
0"
#48750000
b100110 %
1"
#48800000
0"
#48850000
b100111 %
1"
#48900000
0"
#48950000
b101000 %
1"
#49000000
0"
#49050000
b101001 %
1"
#49100000
0"
#49150000
b101010 %
1"
#49200000
0"
#49250000
b101011 %
1"
#49300000
0"
#49350000
b101100 %
1"
#49400000
0"
#49450000
b101101 %
1"
#49500000
0"
#49550000
b101110 %
1"
#49600000
0"
#49650000
b101111 %
1"
#49700000
0"
#49750000
b110000 %
1"
#49800000
0"
#49850000
b110001 %
1"
#49900000
0"
#49950000
b0 %
0!
0$
1"
#50000000
0"
#50050000
b1 %
1"
#50100000
0"
#50150000
b10 %
1"
#50200000
0"
#50250000
b11 %
1"
#50300000
0"
#50350000
b100 %
1"
#50400000
0"
#50450000
b101 %
1"
#50500000
0"
#50550000
b110 %
1"
#50600000
0"
#50650000
b111 %
1"
#50700000
0"
#50750000
b1000 %
1"
#50800000
0"
#50850000
b1001 %
1"
#50900000
0"
#50950000
b1010 %
1"
#51000000
0"
#51050000
b1011 %
1"
#51100000
0"
#51150000
b1100 %
1"
#51200000
0"
#51250000
b1101 %
1"
#51300000
0"
#51350000
b1110 %
1"
#51400000
0"
#51450000
b1111 %
1"
#51500000
0"
#51550000
b10000 %
1"
#51600000
0"
#51650000
b10001 %
1"
#51700000
0"
#51750000
b10010 %
1"
#51800000
0"
#51850000
b10011 %
1"
#51900000
0"
#51950000
b10100 %
1"
#52000000
0"
#52050000
b10101 %
1"
#52100000
0"
#52150000
b10110 %
1"
#52200000
0"
#52250000
b10111 %
1"
#52300000
0"
#52350000
b11000 %
1"
#52400000
0"
#52450000
1!
1$
b11001 %
1"
#52500000
0"
#52550000
b11010 %
1"
#52600000
0"
#52650000
b11011 %
1"
#52700000
0"
#52750000
b11100 %
1"
#52800000
0"
#52850000
b11101 %
1"
#52900000
0"
#52950000
b11110 %
1"
#53000000
0"
#53050000
b11111 %
1"
#53100000
0"
#53150000
b100000 %
1"
#53200000
0"
#53250000
b100001 %
1"
#53300000
0"
#53350000
b100010 %
1"
#53400000
0"
#53450000
b100011 %
1"
#53500000
0"
#53550000
b100100 %
1"
#53600000
0"
#53650000
b100101 %
1"
#53700000
0"
#53750000
b100110 %
1"
#53800000
0"
#53850000
b100111 %
1"
#53900000
0"
#53950000
b101000 %
1"
#54000000
0"
#54050000
b101001 %
1"
#54100000
0"
#54150000
b101010 %
1"
#54200000
0"
#54250000
b101011 %
1"
#54300000
0"
#54350000
b101100 %
1"
#54400000
0"
#54450000
b101101 %
1"
#54500000
0"
#54550000
b101110 %
1"
#54600000
0"
#54650000
b101111 %
1"
#54700000
0"
#54750000
b110000 %
1"
#54800000
0"
#54850000
b110001 %
1"
#54900000
0"
#54950000
b0 %
0!
0$
1"
#55000000
0"
#55050000
b1 %
1"
#55100000
0"
#55150000
b10 %
1"
#55200000
0"
#55250000
b11 %
1"
#55300000
0"
#55350000
b100 %
1"
#55400000
0"
#55450000
b101 %
1"
#55500000
0"
#55550000
b110 %
1"
#55600000
0"
#55650000
b111 %
1"
#55700000
0"
#55750000
b1000 %
1"
#55800000
0"
#55850000
b1001 %
1"
#55900000
0"
#55950000
b1010 %
1"
#56000000
0"
#56050000
b1011 %
1"
#56100000
0"
#56150000
b1100 %
1"
#56200000
0"
#56250000
b1101 %
1"
#56300000
0"
#56350000
b1110 %
1"
#56400000
0"
#56450000
b1111 %
1"
#56500000
0"
#56550000
b10000 %
1"
#56600000
0"
#56650000
b10001 %
1"
#56700000
0"
#56750000
b10010 %
1"
#56800000
0"
#56850000
b10011 %
1"
#56900000
0"
#56950000
b10100 %
1"
#57000000
0"
#57050000
b10101 %
1"
#57100000
0"
#57150000
b10110 %
1"
#57200000
0"
#57250000
b10111 %
1"
#57300000
0"
#57350000
b11000 %
1"
#57400000
0"
#57450000
1!
1$
b11001 %
1"
#57500000
0"
#57550000
b11010 %
1"
#57600000
0"
#57650000
b11011 %
1"
#57700000
0"
#57750000
b11100 %
1"
#57800000
0"
#57850000
b11101 %
1"
#57900000
0"
#57950000
b11110 %
1"
#58000000
0"
#58050000
b11111 %
1"
#58100000
0"
#58150000
b100000 %
1"
#58200000
0"
#58250000
b100001 %
1"
#58300000
0"
#58350000
b100010 %
1"
#58400000
0"
#58450000
b100011 %
1"
#58500000
0"
#58550000
b100100 %
1"
#58600000
0"
#58650000
b100101 %
1"
#58700000
0"
#58750000
b100110 %
1"
#58800000
0"
#58850000
b100111 %
1"
#58900000
0"
#58950000
b101000 %
1"
#59000000
0"
#59050000
b101001 %
1"
#59100000
0"
#59150000
b101010 %
1"
#59200000
0"
#59250000
b101011 %
1"
#59300000
0"
#59350000
b101100 %
1"
#59400000
0"
#59450000
b101101 %
1"
#59500000
0"
#59550000
b101110 %
1"
#59600000
0"
#59650000
b101111 %
1"
#59700000
0"
#59750000
b110000 %
1"
#59800000
0"
#59850000
b110001 %
1"
#59900000
0"
#59950000
b0 %
0!
0$
1"
#60000000
0"
#60050000
b1 %
1"
#60100000
0"
#60150000
b10 %
1"
#60200000
0"
#60250000
b11 %
1"
#60300000
0"
#60350000
b100 %
1"
#60400000
0"
#60450000
b101 %
1"
#60500000
0"
#60550000
b110 %
1"
#60600000
0"
#60650000
b111 %
1"
#60700000
0"
#60750000
b1000 %
1"
#60800000
0"
#60850000
b1001 %
1"
#60900000
0"
#60950000
b1010 %
1"
#61000000
0"
#61050000
b1011 %
1"
#61100000
0"
#61150000
b1100 %
1"
#61200000
0"
#61250000
b1101 %
1"
#61300000
0"
#61350000
b1110 %
1"
#61400000
0"
#61450000
b1111 %
1"
#61500000
0"
#61550000
b10000 %
1"
#61600000
0"
#61650000
b10001 %
1"
#61700000
0"
#61750000
b10010 %
1"
#61800000
0"
#61850000
b10011 %
1"
#61900000
0"
#61950000
b10100 %
1"
#62000000
0"
#62050000
b10101 %
1"
#62100000
0"
#62150000
b10110 %
1"
#62200000
0"
#62250000
b10111 %
1"
#62300000
0"
#62350000
b11000 %
1"
#62400000
0"
#62450000
1!
1$
b11001 %
1"
#62500000
0"
#62550000
b11010 %
1"
#62600000
0"
#62650000
b11011 %
1"
#62700000
0"
#62750000
b11100 %
1"
#62800000
0"
#62850000
b11101 %
1"
#62900000
0"
#62950000
b11110 %
1"
#63000000
0"
#63050000
b11111 %
1"
#63100000
0"
#63150000
b100000 %
1"
#63200000
0"
#63250000
b100001 %
1"
#63300000
0"
#63350000
b100010 %
1"
#63400000
0"
#63450000
b100011 %
1"
#63500000
0"
#63550000
b100100 %
1"
#63600000
0"
